python_marketman/__init__.py
python_marketman/__version__.py
python_marketman/api.py
python_marketman/exceptions.py
python_marketman-0.1.dist-info/LICENSE.txt
python_marketman-0.1.dist-info/METADATA
python_marketman-0.1.dist-info/WHEEL
python_marketman-0.1.dist-info/top_level.txt
python_marketman-0.1.dist-info/RECORD
