Metadata-Version: 2.1
Name: python-marketman
Version: 0.1
Summary: A basic Marketman.com REST API client.
Home-page: https://github.com/LukasKlement/python-marketman
Author: Lukas Klement
Author-email: lukas.klement@me.com
Maintainer: Lukas Klement
Maintainer-email: lukas.klement@me.com
License: Apache 2.0
Keywords: python marketman marketman.com
Platform: UNKNOWN
Classifier: Development Status :: 3 - Alpha
Classifier: License :: OSI Approved :: Apache Software License
Classifier: Intended Audience :: Developers
Classifier: Intended Audience :: System Administrators
Classifier: Operating System :: OS Independent
Classifier: Topic :: Internet :: WWW/HTTP
Classifier: Programming Language :: Python :: 3.6
Classifier: Programming Language :: Python :: 3.7
Classifier: Programming Language :: Python :: 3.8
Classifier: Programming Language :: Python :: Implementation :: PyPy
Requires-Python: >=3.6
